<?xml version="1.0" encoding="utf-8"?>
<!DOCTYPE hibernate-mapping PUBLIC "-//Hibernate/Hibernate Mapping DTD 3.0//EN"
"http://hibernate.sourceforge.net/hibernate-mapping-3.0.dtd">
<!-- 
    Mapping file autogenerated by MyEclipse Persistence Tools
-->
<hibernate-mapping>
    <class name="com.meducation.ORM.PlanSchool" table="plan_school" schema="dbo" catalog="education">
        <id name="id" type="java.lang.Integer">
            <column name="id" />
            <generator class="native" />
        </id>
        <property name="planId" type="string">
            <column name="plan_id" length="50" />
        </property>
        <property name="planName" type="string">
            <column name="plan_name" length="50" />
        </property>
        <property name="planNum" type="string">
            <column name="plan_num" length="50" />
        </property>
        <property name="beginTime" type="string">
            <column name="begin_time" length="50" />
        </property>
        <property name="endTime" type="string">
            <column name="end_time" length="50" />
        </property>
        <property name="introduce" type="string">
            <column name="introduce" />
        </property>
        <property name="belongDistrictName" type="string">
            <column name="belong_district_name" length="50" />
        </property>
        <property name="belongDistrictCode" type="string">
            <column name="belong_district_code" length="50" />
        </property>
        <property name="schoolId" type="string">
            <column name="school_id" length="50" />
        </property>
        <property name="schoolName" type="string">
            <column name="school_name" length="50" />
        </property>
        <property name="schoolCode" type="string">
            <column name="school_code" length="50" />
        </property>
        <property name="schoolType" type="string">
            <column name="school_type" length="50" />
        </property>
        <property name="status" type="string">
            <column name="status" length="50" />
        </property>
        <property name="a1" type="string">
            <column name="a1" length="50" />
        </property>
    </class>
</hibernate-mapping>
